twb/__init__.py
twb/__main__.py
twb/collect.py
twb/config.py
twb/constants.py
twb/utils.py
twb-1.0.2.dist-info/LICENSE
twb-1.0.2.dist-info/METADATA
twb-1.0.2.dist-info/WHEEL
twb-1.0.2.dist-info/entry_points.txt
twb-1.0.2.dist-info/top_level.txt
twb-1.0.2.dist-info/RECORD
