Metadata-Version: 2.1
Name: twb
Version: 1.0.2
Summary: Twitter backup crawler
Author-email: Azalea Gui <me@hydev.org>
License: MIT License
Project-URL: Homepage, https://github.com/one-among-us/TwitterBackup
Keywords: twitter,backup
Classifier: Programming Language :: Python :: 3
Requires-Python: >=3.9
License-File: LICENSE
Requires-Dist: toml (~=0.10.2)
Requires-Dist: tweepy (~=4.12.1)
Requires-Dist: requests (~=2.28.1)
Requires-Dist: hypy-utils (>=1.0.16)
Requires-Dist: importlib-metadata
